Metadata-Version: 2.1
Name: ratingfish
Version: 0.1
Summary: Python wrapper for the RatingFish API
Home-page: https://github.com/abrihter/ratingfish
Download-URL: https://github.com/abrihter/ratingfish/archive/refs/tags/v0.1.tar.gz
Author: abrihter
Author-email: 
License: MIT
Keywords: RATINGFISH,API,WRAPPER
Classifier: Development Status :: 5 - Production/Stable
Classifier: Intended Audience :: Developers
Classifier: Topic :: Software Development :: Build Tools
Classifier: License :: OSI Approved :: MIT License
Classifier: Programming Language :: Python :: 3
License-File: LICENSE
